stickersbot/__init__.py
stickersbot/__main__.py
stickersbot/_version.py
stickersbot/hooks.py
stickersbot/signal.py
stickersbot/util.py
stickersbot-4.2.0.dist-info/licenses/LICENSE
stickersbot-4.2.0.dist-info/METADATA
stickersbot-4.2.0.dist-info/WHEEL
stickersbot-4.2.0.dist-info/entry_points.txt
stickersbot-4.2.0.dist-info/top_level.txt
stickersbot-4.2.0.dist-info/RECORD
