Metadata-Version: 2.4
Name: stickersbot
Version: 4.2.0
Summary: Sticker packs for all your Delta Chat needs
Author-email: adbenitez <adb@merlinux.eu>
Project-URL: Homepage, https://github.com/deltachat-bot/stickersbot
Keywords: deltachat,bot
Classifier: Development Status :: 4 - Beta
Classifier: Programming Language :: Python :: 3
Classifier: License :: OSI Approved :: Mozilla Public License 2.0 (MPL 2.0)
Requires-Python: >=3.10
License-File: LICENSE
Requires-Dist: deltabot-cli<9.0,>=8.0.0
Requires-Dist: signalstickers-client>=3.3.0
Requires-Dist: emoji>=2.15.0
Requires-Dist: cachelib>=0.13.0
Requires-Dist: requests<3.0,>=2.32.5
Requires-Dist: pillow>=12.0.0
Requires-Dist: rembg[cpu]>=2.0.68
Provides-Extra: dev
Requires-Dist: black; extra == "dev"
Requires-Dist: mypy; extra == "dev"
Requires-Dist: isort; extra == "dev"
Requires-Dist: pylint; extra == "dev"
Requires-Dist: pylama; extra == "dev"
Requires-Dist: pytest; extra == "dev"
Requires-Dist: types-emoji; extra == "dev"
Requires-Dist: types-requests; extra == "dev"
Requires-Dist: setuptools; extra == "dev"
Dynamic: license-file
